requirements.txt
examples/__init__.py
examples/how_predictors_help_each_other.py
examples/improving_sections.py
examples/visualize_a_doc.py
papermage/__init__.py
papermage/py.typed
papermage/magelib/__init__.py
papermage/magelib/box.py
papermage/magelib/document.py
papermage/magelib/entity.py
papermage/magelib/image.py
papermage/magelib/indexer.py
papermage/magelib/layer.py
papermage/magelib/metadata.py
papermage/magelib/names.py
papermage/magelib/span.py
papermage/parsers/__init__.py
papermage/parsers/grobid_parser.py
papermage/parsers/parser.py
papermage/parsers/pdfplumber_parser.py
papermage/predictors/__init__.py
papermage/predictors/block_predictors.py
papermage/predictors/formula_predictors.py
papermage/predictors/sentence_predictors.py
papermage/predictors/span_qa_predictors.py
papermage/predictors/token_predictors.py
papermage/predictors/vila_predictors.py
papermage/predictors/word_predictors.py
papermage/predictors/base_predictors/__init__.py
papermage/predictors/base_predictors/api_predictors.py
papermage/predictors/base_predictors/base_predictor.py
papermage/predictors/base_predictors/hf_predictors.py
papermage/predictors/base_predictors/lp_predictors.py
papermage/predictors/base_predictors/sklearn_predictors.py
papermage/predictors/base_predictors/spacy_predictors.py
papermage/rasterizers/__init__.py
papermage/rasterizers/rasterizer.py
papermage/recipes/__init__.py
papermage/recipes/core_recipe.py
papermage/recipes/minimal_pdf_recipe.py
papermage/recipes/recipe.py
papermage/recipes/text_recipe.py
papermage/trainers/__init__.py
papermage/trainers/bio_tagger_predictor_trainer.py
papermage/utils/__init__.py
papermage/utils/annotate.py
papermage/utils/merge.py
papermage/utils/text.py
papermage/utils/version.py
papermage/visualizers/__init__.py
papermage/visualizers/visualizer.py
scripts/evaluation.py
scripts/get_thumbnails_for_papers.py
tests/__init__.py
tests/test_magelib/__init__.py
tests/test_magelib/test_box.py
tests/test_magelib/test_document.py
papermage-0.20.0.dist-info/LICENSE
papermage-0.20.0.dist-info/METADATA
papermage-0.20.0.dist-info/WHEEL
papermage-0.20.0.dist-info/top_level.txt
papermage-0.20.0.dist-info/RECORD
