Metadata-Version: 2.1
Name: papermage
Version: 0.20.0
Summary: Papermage. Casting magic over scientific PDFs.
Author-email: Kyle Lo <kylel@allenai.org>, Luca Soldaini <luca@soldaini.net>, Shannon Zejiang Shen <zejiangshen@gmail.com>, Ben Newman <blnewman@stanford.edu>, Russell Authur <russell.authur@gmail.com>, Stefan Candra <stefanc@allenai.org>, Yoganand Chandrasekhar <yogic@allenai.org>, Regan Huff <reganh@allenai.org>, Amanpreet Singh <amans@allenai.org>, Chris Wilhelm <chrisw@allenai.org>, Angele Zamarron <angelez@allenai.org>
Maintainer-email: Kyle Lo <kylel@allenai.org>, Luca Soldaini <luca@soldaini.net>
License: Apache-2.0
Project-URL: Homepage, https://www.github.com/allenai/papermage
Project-URL: Repository, https://www.github.com/allenai/papermage
Project-URL: Bug Tracker, https://www.github.com/allenai/papermage/issues
Classifier: Development Status :: 3 - Alpha
Classifier: Typing :: Typed
Classifier: Programming Language :: Python :: Implementation :: CPython
Classifier: Programming Language :: Python :: Implementation :: PyPy
Requires-Python: >=3.8
License-File: LICENSE
Requires-Dist: tqdm
Requires-Dist: pdf2image
Requires-Dist: pdfplumber==0.7.4
Requires-Dist: requests
Requires-Dist: numpy>=1.23.2
Requires-Dist: scipy>=1.9.0
Requires-Dist: ncls==0.0.68
Requires-Dist: necessary>=0.3.2
Requires-Dist: grobid-client-python==0.0.5
Requires-Dist: charset-normalizer
Provides-Extra: dev
Requires-Dist: pytest; extra == "dev"
Requires-Dist: pytest-xdist; extra == "dev"
Requires-Dist: pytest-cov; extra == "dev"
Requires-Dist: mypy>=0.971; extra == "dev"
Provides-Extra: visualizers
Requires-Dist: layoutparser==0.3.4; extra == "visualizers"
Provides-Extra: predictors
Requires-Dist: thefuzz[speedup]; extra == "predictors"
Requires-Dist: scikit-learn>=1.3.0; extra == "predictors"
Requires-Dist: xgboost>=1.6.2; extra == "predictors"
Requires-Dist: spacy>=3.4.2; extra == "predictors"
Requires-Dist: pysbd==0.3.4; extra == "predictors"
Requires-Dist: tokenizers==0.13.3; extra == "predictors"
Requires-Dist: torch>=2.0.1; extra == "predictors"
Requires-Dist: torchvision>=0.15.2; extra == "predictors"
Requires-Dist: layoutparser==0.3.4; extra == "predictors"
Requires-Dist: transformers==4.31.0; extra == "predictors"
Requires-Dist: smashed==0.1.10; extra == "predictors"
Requires-Dist: pytorch-lightning>=2.0.5; extra == "predictors"
Requires-Dist: springs==1.13.0; extra == "predictors"
Requires-Dist: wandb>=0.15.7; extra == "predictors"
Requires-Dist: seqeval==1.2.2; extra == "predictors"
Requires-Dist: effdet==0.3.0; extra == "predictors"
Requires-Dist: vila==0.5.0; extra == "predictors"
Provides-Extra: decontext
Requires-Dist: decontext==0.1.6; extra == "decontext"
Provides-Extra: production
Requires-Dist: optimum[onnxruntime]==1.10.0; extra == "production"
